footprints/__init__.py
footprints/access.py
footprints/collectors.py
footprints/config.py
footprints/doc.py
footprints/loggers.py
footprints/priorities.py
footprints/proxies.py
footprints/reporting.py
footprints/stdtypes.py
footprints/util.py
footprints-2.0.0.dist-info/LICENSE-en.txt
footprints-2.0.0.dist-info/LICENSE.txt
footprints-2.0.0.dist-info/METADATA
footprints-2.0.0.dist-info/WHEEL
footprints-2.0.0.dist-info/top_level.txt
footprints-2.0.0.dist-info/RECORD
