Metadata-Version: 2.1
Name: footprints
Version: 2.0.0
Summary: A generic multi-purpose fabric for objects with tunable footprints
Author-email: The Vortex Team <vortex.support@meteo.fr>
License: CECILL-C
Project-URL: repository, https://github.com/UMR-CNRM/footprints
Classifier: Development Status :: 4 - Beta
Classifier: License :: CeCILL-C Free Software License Agreement (CECILL-C)
Requires-Python: >=3.7
License-File: LICENSE-en.txt
License-File: LICENSE.txt
Requires-Dist: bronx
Provides-Extra: docs
Requires-Dist: sphinx ; extra == 'docs'
